cvxmg/cvxmg.py
cvxmg-2.0.0.dist-info/LICENSE
cvxmg-2.0.0.dist-info/METADATA
cvxmg-2.0.0.dist-info/WHEEL
cvxmg-2.0.0.dist-info/top_level.txt
cvxmg-2.0.0.dist-info/RECORD
