Metadata-Version: 2.1
Name: cvxmg
Version: 2.0.0
Summary: Planning of Microgrids considering Demand Side Management Strategies using Disciplined Convex Deterministic and StochasticProgramming
Home-page: https://github.com/juancaoviedo/cvxmg
Author: Juan Carlos Oviedo Cepeda
Author-email: juan.oviedo@correo.uis.edu.co
License: MIT
Download-URL: https://github.com/juancaoviedo/cvxmg.git
Keywords: convex,microgrids,optimization,stochastic,demand-side management
Platform: UNKNOWN
Classifier: Development Status :: 3 - Alpha
Classifier: Intended Audience :: Developers
Classifier: Topic :: Software Development :: Build Tools
Classifier: License :: OSI Approved :: MIT License
Classifier: Programming Language :: Python :: 3.6
Classifier: Programming Language :: Python :: 3.7
Requires-Dist: numpy
Requires-Dist: pandas
Requires-Dist: cvxpy
Requires-Dist: matplotlib
